getproclist/README.md
getproclist/__init__.py
getproclist/requirements.txt
getproclist/thirdparty.json
getproclist-0.10.dist-info/LICENSE.rst
getproclist-0.10.dist-info/METADATA
getproclist-0.10.dist-info/WHEEL
getproclist-0.10.dist-info/top_level.txt
getproclist-0.10.dist-info/RECORD
