Metadata-Version: 2.1
Name: getproclist
Version: 0.10
Summary: Retrieves the list of processes using the 'wmic' command and return the data as a pandas DataFrame
Home-page: https://github.com/hansalemaos/getproclist
Author: Johannes Fischer
Author-email: aulasparticularesdealemaosp@gmail.com
License: MIT
Keywords: wmic,process,pid
Classifier: Development Status :: 4 - Beta
Classifier: Programming Language :: Python :: 3 :: Only
Classifier: Programming Language :: Python :: 3.10
Classifier: Topic :: Software Development :: Libraries :: Python Modules
Classifier: Topic :: Utilities
License-File: LICENSE.rst
Requires-Dist: a-pandas-ex-less-memory-more-speed
Requires-Dist: flatten-everything
Requires-Dist: pandas
Requires-Dist: subprocesskiller
